setup.py
tractor_common/__init__.py
tractor_common/broker.py
tractor_common/database.py
tractor_common.egg-info/PKG-INFO
tractor_common.egg-info/SOURCES.txt
tractor_common.egg-info/dependency_links.txt
tractor_common.egg-info/requires.txt
tractor_common.egg-info/top_level.txt