Metadata-Version: 1.1
Name: tractor-common
Version: 1.1.0
Summary: Utilities for captain-tractor project
Home-page: http://github.com/tatiana/captain-tractor
Author: Tatiana Al-Chueyr <tatiana.alchueyr@gmail.com>
Author-email: UNKNOWN
License: MIT License
Download-URL: http://pypi.python.org/pypi/tractor_common
Platform: UNKNOWN
Classifier: Development Status :: 5 - Production/Stable
Classifier: Environment :: Web Environment
Classifier: Intended Audience :: Developers
Classifier: Operating System :: OS Independent
Classifier: Programming Language :: Python
